steamboat/__init__.py
steamboat/cli/__init__.py
steamboat/cli/repos/__init__.py
steamboat/cli/repos/gisaid/__init__.py
steamboat/cli/repos/gisaid/batch.py
steamboat/cli/repos/nwss/__init__.py
steamboat/cli/repos/nwss/batch.py
steamboat/io/__init__.py
steamboat/io/check.py
steamboat/io/fasta.py
steamboat/io/table.py
steamboat/io/yaml.py
steamboat/repos/__init__.py
steamboat/repos/gisaid.py
steamboat/repos/nwss.py
steamboat/utils/__init__.py
steamboat/utils.py
steamboat_binf-1.1.1.dist-info/LICENSE
steamboat_binf-1.1.1.dist-info/METADATA
steamboat_binf-1.1.1.dist-info/WHEEL
steamboat_binf-1.1.1.dist-info/entry_points.txt
steamboat_binf-1.1.1.dist-info/RECORD
