Metadata-Version: 2.3
Name: steamboat-binf
Version: 1.1.1
Summary: A collection of tools/scripts for microbial bioinformatics
License: MIT
Keywords: bioinformatics
Author: Robert A. Petit III
Author-email: robbie.petit@gmail.com
Requires-Python: >=3.10.0,<4.0.0
Classifier: License :: OSI Approved :: MIT License
Classifier: Programming Language :: Python :: 3
Classifier: Programming Language :: Python :: 3.10
Classifier: Programming Language :: Python :: 3.11
Classifier: Programming Language :: Python :: 3.12
Classifier: Programming Language :: Python :: 3.13
Requires-Dist: biopython (>=1.84,<2.0)
Requires-Dist: executor (>=23.2,<24.0)
Requires-Dist: pyyaml (>=6.0.2,<7.0.0)
Requires-Dist: rich (>=13.3.1,<14.0.0)
Requires-Dist: rich-click (>=1.6.1,<2.0.0)
Project-URL: Homepage, https://github.com/rpetit3/steamboat-py
Project-URL: Repository, https://github.com/rpetit3/steamboat-py
